{
  "metadata": {
    "toolPackage": "@microsoft/api-extractor",
    "toolVersion": "7.52.8",
    "schemaVersion": 1011,
    "oldestForwardsCompatibleVersion": 1001,
    "tsdocConfig": {
      "$schema": "https://developer.microsoft.com/json-schemas/tsdoc/v0/tsdoc.schema.json",
      "noStandardTags": true,
      "tagDefinitions": [
        {
          "tagName": "@alpha",
          "syntaxKind": "modifier"
        },
        {
          "tagName": "@beta",
          "syntaxKind": "modifier"
        },
        {
          "tagName": "@defaultValue",
          "syntaxKind": "block"
        },
        {
          "tagName": "@decorator",
          "syntaxKind": "block",
          "allowMultiple": true
        },
        {
          "tagName": "@deprecated",
          "syntaxKind": "block"
        },
        {
          "tagName": "@eventProperty",
          "syntaxKind": "modifier"
        },
        {
          "tagName": "@example",
          "syntaxKind": "block",
          "allowMultiple": true
        },
        {
          "tagName": "@experimental",
          "syntaxKind": "modifier"
        },
        {
          "tagName": "@inheritDoc",
          "syntaxKind": "inline"
        },
        {
          "tagName": "@internal",
          "syntaxKind": "modifier"
        },
        {
          "tagName": "@label",
          "syntaxKind": "inline"
        },
        {
          "tagName": "@link",
          "syntaxKind": "inline",
          "allowMultiple": true
        },
        {
          "tagName": "@override",
          "syntaxKind": "modifier"
        },
        {
          "tagName": "@packageDocumentation",
          "syntaxKind": "modifier"
        },
        {
          "tagName": "@param",
          "syntaxKind": "block",
          "allowMultiple": true
        },
        {
          "tagName": "@privateRemarks",
          "syntaxKind": "block"
        },
        {
          "tagName": "@public",
          "syntaxKind": "modifier"
        },
        {
          "tagName": "@readonly",
          "syntaxKind": "modifier"
        },
        {
          "tagName": "@remarks",
          "syntaxKind": "block"
        },
        {
          "tagName": "@returns",
          "syntaxKind": "block"
        },
        {
          "tagName": "@sealed",
          "syntaxKind": "modifier"
        },
        {
          "tagName": "@see",
          "syntaxKind": "block"
        },
        {
          "tagName": "@throws",
          "syntaxKind": "block",
          "allowMultiple": true
        },
        {
          "tagName": "@typeParam",
          "syntaxKind": "block",
          "allowMultiple": true
        },
        {
          "tagName": "@virtual",
          "syntaxKind": "modifier"
        },
        {
          "tagName": "@group",
          "syntaxKind": "block"
        }
      ],
      "reportUnsupportedHtmlElements": false
    }
  },
  "kind": "Package",
  "canonicalReference": "@contember/react-ui-lib!",
  "docComment": "",
  "name": "@contember/react-ui-lib",
  "preserveMemberOrder": false,
  "members": [
    {
      "kind": "EntryPoint",
      "canonicalReference": "@contember/react-ui-lib!",
      "name": "",
      "preserveMemberOrder": false,
      "members": [
        {
          "kind": "Function",
          "canonicalReference": "@contember/react-ui-lib!formatImageResizeUrl:function(1)",
          "docComment": "/**\n * formatImageResizeUrl - Generates optimized image URLs\n *\n * #### Purpose Creates URLs for on-demand image processing\n *\n * #### Features - Only processes Contember-hosted images - Maintains original URL for external images - Defaults to contain fit and auto format - URL-encoded transformation parameters\n *\n * #### Example\n * ```ts\n * formatImageResizeUrl('https://cdn.cntmbr.com/image.jpg', { width: 300 })\n * // 'https://cdn.cntmbr.com/cdn-cgi/image/width=300,fit=contain,f=auto/image.jpg'\n * ```\n *\n */\n",
          "excerptTokens": [
            {
              "kind": "Content",
              "text": "formatImageResizeUrl: (src: "
            },
            {
              "kind": "Content",
              "text": "string"
            },
            {
              "kind": "Content",
              "text": ", options?: "
            },
            {
              "kind": "Reference",
              "text": "ImageResizeOptions",
              "canonicalReference": "@contember/react-ui-lib!ImageResizeOptions:interface"
            },
            {
              "kind": "Content",
              "text": ") => "
            },
            {
              "kind": "Content",
              "text": "string"
            }
          ],
          "fileUrlPath": "src/images/formatImageResizeUrl.ts",
          "returnTypeTokenRange": {
            "startIndex": 5,
            "endIndex": 6
          },
          "releaseTag": "Public",
          "overloadIndex": 1,
          "parameters": [
            {
              "parameterName": "src",
              "parameterTypeTokenRange": {
                "startIndex": 1,
                "endIndex": 2
              },
              "isOptional": false
            },
            {
              "parameterName": "options",
              "parameterTypeTokenRange": {
                "startIndex": 3,
                "endIndex": 4
              },
              "isOptional": true
            }
          ],
          "name": "formatImageResizeUrl"
        },
        {
          "kind": "Interface",
          "canonicalReference": "@contember/react-ui-lib!ImageResizeOptions:interface",
          "docComment": "",
          "excerptTokens": [
            {
              "kind": "Content",
              "text": "export interface ImageResizeOptions "
            }
          ],
          "fileUrlPath": "src/images/formatImageResizeUrl.ts",
          "releaseTag": "Public",
          "name": "ImageResizeOptions",
          "preserveMemberOrder": false,
          "members": [
            {
              "kind": "PropertySignature",
              "canonicalReference": "@contember/react-ui-lib!ImageResizeOptions#blur:member",
              "docComment": "/**\n * Gaussian blur radius (0-100)\n */\n",
              "excerptTokens": [
                {
                  "kind": "Content",
                  "text": "blur?: "
                },
                {
                  "kind": "Content",
                  "text": "number"
                },
                {
                  "kind": "Content",
                  "text": ";"
                }
              ],
              "isReadonly": false,
              "isOptional": true,
              "releaseTag": "Public",
              "name": "blur",
              "propertyTypeTokenRange": {
                "startIndex": 1,
                "endIndex": 2
              }
            },
            {
              "kind": "PropertySignature",
              "canonicalReference": "@contember/react-ui-lib!ImageResizeOptions#fit:member",
              "docComment": "/**\n * Resize behavior\n */\n",
              "excerptTokens": [
                {
                  "kind": "Content",
                  "text": "fit?: "
                },
                {
                  "kind": "Content",
                  "text": "'scale-down' | 'contain' | 'cover' | 'crop' | 'pad'"
                },
                {
                  "kind": "Content",
                  "text": ";"
                }
              ],
              "isReadonly": false,
              "isOptional": true,
              "releaseTag": "Public",
              "name": "fit",
              "propertyTypeTokenRange": {
                "startIndex": 1,
                "endIndex": 2
              }
            },
            {
              "kind": "PropertySignature",
              "canonicalReference": "@contember/react-ui-lib!ImageResizeOptions#format:member",
              "docComment": "/**\n * Output format\n */\n",
              "excerptTokens": [
                {
                  "kind": "Content",
                  "text": "format?: "
                },
                {
                  "kind": "Content",
                  "text": "'auto' | 'avif' | 'webp' | 'jpeg' | 'baseline-jpeg' | 'json'"
                },
                {
                  "kind": "Content",
                  "text": ";"
                }
              ],
              "isReadonly": false,
              "isOptional": true,
              "releaseTag": "Public",
              "name": "format",
              "propertyTypeTokenRange": {
                "startIndex": 1,
                "endIndex": 2
              }
            },
            {
              "kind": "PropertySignature",
              "canonicalReference": "@contember/react-ui-lib!ImageResizeOptions#height:member",
              "docComment": "/**\n * Target height in pixels\n */\n",
              "excerptTokens": [
                {
                  "kind": "Content",
                  "text": "height?: "
                },
                {
                  "kind": "Content",
                  "text": "number"
                },
                {
                  "kind": "Content",
                  "text": ";"
                }
              ],
              "isReadonly": false,
              "isOptional": true,
              "releaseTag": "Public",
              "name": "height",
              "propertyTypeTokenRange": {
                "startIndex": 1,
                "endIndex": 2
              }
            },
            {
              "kind": "PropertySignature",
              "canonicalReference": "@contember/react-ui-lib!ImageResizeOptions#quality:member",
              "docComment": "/**\n * Output quality (1-100)\n */\n",
              "excerptTokens": [
                {
                  "kind": "Content",
                  "text": "quality?: "
                },
                {
                  "kind": "Content",
                  "text": "number"
                },
                {
                  "kind": "Content",
                  "text": ";"
                }
              ],
              "isReadonly": false,
              "isOptional": true,
              "releaseTag": "Public",
              "name": "quality",
              "propertyTypeTokenRange": {
                "startIndex": 1,
                "endIndex": 2
              }
            },
            {
              "kind": "PropertySignature",
              "canonicalReference": "@contember/react-ui-lib!ImageResizeOptions#width:member",
              "docComment": "/**\n * Target width in pixels\n */\n",
              "excerptTokens": [
                {
                  "kind": "Content",
                  "text": "width?: "
                },
                {
                  "kind": "Content",
                  "text": "number"
                },
                {
                  "kind": "Content",
                  "text": ";"
                }
              ],
              "isReadonly": false,
              "isOptional": true,
              "releaseTag": "Public",
              "name": "width",
              "propertyTypeTokenRange": {
                "startIndex": 1,
                "endIndex": 2
              }
            }
          ],
          "extendsTokenRanges": []
        }
      ]
    }
  ]
}
